.gitignore
MANIFEST.in
README.rst
bootstrap.py
buildout.cfg
setup.py
collective/__init__.py
collective.portlet.twittermultistream.egg-info/PKG-INFO
collective.portlet.twittermultistream.egg-info/SOURCES.txt
collective.portlet.twittermultistream.egg-info/dependency_links.txt
collective.portlet.twittermultistream.egg-info/entry_points.txt
collective.portlet.twittermultistream.egg-info/namespace_packages.txt
collective.portlet.twittermultistream.egg-info/not-zip-safe
collective.portlet.twittermultistream.egg-info/requires.txt
collective.portlet.twittermultistream.egg-info/top_level.txt
collective/portlet/__init__.py
collective/portlet/twittermultistream/__init__.py
collective/portlet/twittermultistream/configure.zcml
collective/portlet/twittermultistream/twittermultistream.css
collective/portlet/twittermultistream/twittermultistream.pt
collective/portlet/twittermultistream/twittermultistream.py
collective/portlet/twittermultistream/upgrades.py
collective/portlet/twittermultistream/upgrades.zcml
collective/portlet/twittermultistream/version.txt
collective/portlet/twittermultistream/profiles/default/cssregistry.xml
collective/portlet/twittermultistream/profiles/default/jsregistry.xml
collective/portlet/twittermultistream/profiles/default/metadata.xml
collective/portlet/twittermultistream/profiles/default/portlets.xml
collective/portlet/twittermultistream/tests/__init__.py
collective/portlet/twittermultistream/tests/base.py
collective/portlet/twittermultistream/tests/test_portlet.py
docs/HISTORY.txt
docs/INSTALL.txt
docs/LICENSE.GPL
docs/LICENSE.txt