Metadata-Version: 1.0
Name: collective.portlet.twittermultistream
Version: 1.2
Summary: Twitter Multi Stream portlet for Plone
Home-page: https://github.com/collective/collective.portlet.twittermultistream
Author: JeanMichel FRANCOIS aka toutpt
Author-email: toutpt@gmail.com
License: GPL
Keywords: Plone Twitter Portlet
Platform: UNKNOWN
Classifier: Programming Language :: Python
Classifier: Framework :: Plone
Classifier: Framework :: Plone :: 4.0
Classifier: Framework :: Plone :: 4.1
Classifier: Framework :: Plone :: 4.2
